unchained_editor/__init__.py
unchained_editor/admin.py
unchained_editor/apps.py
unchained_editor/fields.py
unchained_editor/migrations/__init__.py
unchained_editor/models.py
unchained_editor/static/unchained_editor/css/styles.css
unchained_editor/static/unchained_editor/js/script.js
unchained_editor/templates/unchained_editor/editor.html
unchained_editor/tests.py
unchained_editor/urls.py
unchained_editor/views.py
unchained_editor/widgets.py
unchained_editor-0.1.0.dist-info/LICENSE
unchained_editor-0.1.0.dist-info/METADATA
unchained_editor-0.1.0.dist-info/WHEEL
unchained_editor-0.1.0.dist-info/RECORD
