Metadata-Version: 2.1
Name: unchained-editor
Version: 0.1.0
Summary: A custom Django WYSIWYG editor widget.
License: GNUv3
Author: Kamila Kolpashnikova
Author-email: kamilakolpashnikova@gmail.com
Requires-Python: >=3.10,<4.0
Classifier: License :: Other/Proprietary License
Classifier: Programming Language :: Python :: 3
Classifier: Programming Language :: Python :: 3.10
Classifier: Programming Language :: Python :: 3.11
Classifier: Programming Language :: Python :: 3.12
Classifier: Programming Language :: Python :: 3.13
Requires-Dist: Django (>=5.1.4,<6.0.0)
Requires-Dist: cryptography (>=41.0.0,<42.0.0)
Requires-Dist: pyjwt (>=2.6.0,<3.0.0)
